synr/__init__.py
synr/ast.py
synr/compiler.py
synr/diagnostic_context.py
synr/transformer.py
synr-0.6.0.dist-info/LICENSE
synr-0.6.0.dist-info/WHEEL
synr-0.6.0.dist-info/METADATA
synr-0.6.0.dist-info/RECORD
