Metadata-Version: 2.1
Name: synr
Version: 0.6.0
Summary: A consistent AST for Python
Author: Jared Roesch
Author-email: jroesch@octoml.ai
Requires-Python: >=3.6.2,<4.0.0
Classifier: Programming Language :: Python :: 3
Classifier: Programming Language :: Python :: 3.10
Classifier: Programming Language :: Python :: 3.7
Classifier: Programming Language :: Python :: 3.8
Classifier: Programming Language :: Python :: 3.9
Requires-Dist: attrs
